CMakeLists.txt
LICENSE
MANIFEST.in
README.md
VERSION
cygtrace.cpp
cygtrace.h
cygtrace.pc.in
cygtrace_export.h
cygtrace_pybind11.cpp
cygtrace_python.c
pyproject.toml
requirements.txt
setup.py
cygtrace.egg-info/PKG-INFO
cygtrace.egg-info/SOURCES.txt
cygtrace.egg-info/dependency_links.txt
cygtrace.egg-info/entry_points.txt
cygtrace.egg-info/top_level.txt
cygtrace_lib/__init__.py