Metadata-Version: 2.1
Name: cygtrace
Version: 0.0.1
Summary: gcc instrumentation based tracer for c/c++/pybind11
Home-page: https://github.com/CreeperLin/cygtrace
Author: Yunfeng Lin
Author-email: linyunfeng@sjtu.edu.cn
Classifier: Programming Language :: Python :: 3
Classifier: License :: OSI Approved :: MIT License
Classifier: Operating System :: POSIX :: Linux
Classifier: Topic :: Software Development :: Libraries
Classifier: Topic :: Software Development :: Quality Assurance
Classifier: Topic :: Software Development :: Bug Tracking
Classifier: Topic :: System :: Logging
Requires-Python: >=3.6
License-File: LICENSE
